typing_checked/__init__.py
typing_checked/easymode.py
typing_checked-1.0.0.dist-info/LICENSE.txt
typing_checked-1.0.0.dist-info/METADATA
typing_checked-1.0.0.dist-info/WHEEL
typing_checked-1.0.0.dist-info/top_level.txt
typing_checked-1.0.0.dist-info/RECORD
