Metadata-Version: 2.1
Name: typing_checked
Version: 1.0.0
Summary: typing_checked
Author-email: Johannes <johannes-programming@posteo.org>
License: The MIT License (MIT)
Project-URL: Download, https://pypi.org/project/typing-checked/#files
Project-URL: Source, https://github.com/johannes-programming/typing_checked
Classifier: License :: OSI Approved :: MIT License
Classifier: Programming Language :: Python
Classifier: Programming Language :: Python :: 3
Requires-Python: >=3.11
License-File: LICENSE.txt
